{"v":"5.5.9","fr":29.9700012207031,"ip":0,"op":150.000006109625,"w":500,"h":500,"nm":"TETE MORTE/igor","ddd":0,"assets":[],"layers":[{"ddd":0,"ind":1,"ty":4,"nm":"OTHER BRAS/igor Silhouettes 2","sr":1,"ks":{"o":{"a":0,"k":100,"ix":11},"r":{"a":1,"k":[{"i":{"x":[0.667],"y":[1]},"o":{"x":[0.333],"y":[0]},"t":7,"s":[33]},{"t":15.0000006109625,"s":[-32]}],"ix":10},"p":{"a":0,"k":[104,220,0],"ix":2},"a":{"a":0,"k":[40.5,6.5,0],"ix":1},"s":{"a":0,"k":[100,100,100],"ix":6}},"ao":0,"shapes":[{"ty":"gr","it":[{"ind":0,"ty":"sh","ix":1,"ks":{"a":1,"k":[{"i":{"x":0.667,"y":1},"o":{"x":0.333,"y":0},"t":25,"s":[{"i":[[4.876,0.689],[0,0],[1.54,0.428],[-0.681,-3.361],[-11.157,-4.318],[2.226,4.929]],"o":[[-4.876,-0.689],[0,0],[-1.696,-0.472],[1.299,6.413],[11.157,4.318],[-2.226,-4.929]],"v":[[8.112,234.774],[3.343,240.048],[0.2,238.551],[-2.434,241.744],[7.637,253.933],[14.155,249.162]],"c":true}]},{"t":35.0000014255792,"s":[{"i":[[4.876,0.689],[0,0],[4.172,-1.66],[-3.032,-4.66],[0.353,11.958],[9.912,13.859]],"o":[[-4.876,-0.689],[0,0],[-2.86,1.138],[7.409,11.385],[-0.319,-10.812],[-6.86,-9.592]],"v":[[10.921,233.581],[2.918,237.424],[-6.66,234.527],[-6.965,245.693],[12.302,261.565],[18.714,250.832]],"c":true}]}],"ix":2},"nm":"Tracé 1","mn":"ADBE Vector Shape - Group","hd":false},{"ty":"st","c":{"a":0,"k":[0.862744978362,0.345097979377,0.490195988674,1],"ix":3},"o":{"a":0,"k":100,"ix":4},"w":{"a":0,"k":0,"ix":5},"lc":1,"lj":1,"ml":4,"bm":0,"nm":"Contour 1","mn":"ADBE Vector Graphic - Stroke","hd":false},{"ty":"fl","c":{"a":0,"k":[0.698039215686,0.01568627451,0.01568627451,1],"ix":4},"o":{"a":0,"k":100,"ix":5},"r":1,"bm":0,"nm":"Fond 1","mn":"ADBE Vector Graphic - Fill","hd":false},{"ty":"tr","p":{"a":0,"k":[0,0],"ix":2},"a":{"a":0,"k":[0,0],"ix":1},"s":{"a":0,"k":[100,100],"ix":3},"r":{"a":0,"k":0,"ix":6},"o":{"a":1,"k":[{"i":{"x":[0.667],"y":[1]},"o":{"x":[0.333],"y":[0]},"t":22,"s":[0]},{"t":23.0000009368092,"s":[100]}],"ix":7},"sk":{"a":0,"k":0,"ix":4},"sa":{"a":0,"k":0,"ix":5},"nm":"Transformer "}],"nm":"Forme 4","np":3,"cix":2,"bm":0,"ix":1,"mn":"ADBE Vector Group","hd":false},{"ty":"gr","it":[{"ind":0,"ty":"sh","ix":1,"ks":{"a":1,"k":[{"i":{"x":0.667,"y":1},"o":{"x":0.333,"y":0},"t":22,"s":[{"i":[[0,0],[-3.286,-3.233]],"o":[[0,0],[3.286,3.233]],"v":[[90.173,131.284],[85.801,138.28]],"c":true}]},{"t":23.0000009368092,"s":[{"i":[[0,0],[-3.286,-3.233]],"o":[[0,0],[3.286,3.233]],"v":[[90.173,131.284],[85.801,138.28]],"c":true}]}],"ix":2},"nm":"Tracé 1","mn":"ADBE Vector Shape - Group","hd":false},{"ty":"st","c":{"a":0,"k":[0.862744978362,0.345097979377,0.490195988674,1],"ix":3},"o":{"a":0,"k":100,"ix":4},"w":{"a":0,"k":0,"ix":5},"lc":1,"lj":1,"ml":4,"bm":0,"nm":"Contour 1","mn":"ADBE Vector Graphic - Stroke","hd":false},{"ty":"fl","c":{"a":0,"k":[0.698039215686,0.01568627451,0.01568627451,1],"ix":4},"o":{"a":0,"k":100,"ix":5},"r":1,"bm":0,"nm":"Fond 1","mn":"ADBE Vector Graphic - Fill","hd":false},{"ty":"tr","p":{"a":1,"k":[{"i":{"x":0.667,"y":1},"o":{"x":0.333,"y":0},"t":29,"s":[100.615,115.757],"to":[-15.103,21.593],"ti":[15.103,-21.593]},{"t":35.0000014255792,"s":[9.998,245.318]}],"ix":2},"a":{"a":0,"k":[88.23,135.915],"ix":1},"s":{"a":0,"k":[100,100],"ix":3},"r":{"a":0,"k":0,"ix":6},"o":{"a":0,"k":100,"ix":7},"sk":{"a":0,"k":0,"ix":4},"sa":{"a":0,"k":0,"ix":5},"nm":"Transformer "}],"nm":"Forme 3","np":3,"cix":2,"bm":0,"ix":2,"mn":"ADBE Vector Group","hd":false},{"ty":"gr","it":[{"ind":0,"ty":"sh","ix":1,"ks":{"a":0,"k":{"i":[[0,0],[-3.286,-3.233]],"o":[[0,0],[3.286,3.233]],"v":[[90.173,131.284],[85.801,138.28]],"c":true},"ix":2},"nm":"Tracé 1","mn":"ADBE Vector Shape - Group","hd":false},{"ty":"st","c":{"a":0,"k":[0.862744978362,0.345097979377,0.490195988674,1],"ix":3},"o":{"a":0,"k":100,"ix":4},"w":{"a":0,"k":0,"ix":5},"lc":1,"lj":1,"ml":4,"bm":0,"nm":"Contour 1","mn":"ADBE Vector Graphic - Stroke","hd":false},{"ty":"fl","c":{"a":0,"k":[0.698039215686,0.01568627451,0.01568627451,1],"ix":4},"o":{"a":0,"k":100,"ix":5},"r":1,"bm":0,"nm":"Fond 1","mn":"ADBE Vector Graphic - Fill","hd":false},{"ty":"tr","p":{"a":1,"k":[{"i":{"x":0.667,"y":1},"o":{"x":0.333,"y":0},"t":23,"s":[100.615,115.757],"to":[-15.103,21.593],"ti":[15.103,-21.593]},{"t":29.0000011811942,"s":[9.998,245.318]}],"ix":2},"a":{"a":0,"k":[88.23,135.915],"ix":1},"s":{"a":0,"k":[100,100],"ix":3},"r":{"a":0,"k":0,"ix":6},"o":{"a":0,"k":100,"ix":7},"sk":{"a":0,"k":0,"ix":4},"sa":{"a":0,"k":0,"ix":5},"nm":"Transformer "}],"nm":"Forme 2","np":3,"cix":2,"bm":0,"ix":3,"mn":"ADBE Vector Group","hd":false},{"ty":"gr","it":[{"ind":0,"ty":"sh","ix":1,"ks":{"a":0,"k":{"i":[[0,0],[-6.83,-8.124]],"o":[[0,0],[1.857,2.209]],"v":[[89.868,129.177],[84.555,139.565]],"c":true},"ix":2},"nm":"Tracé 1","mn":"ADBE Vector Shape - Group","hd":false},{"ty":"st","c":{"a":0,"k":[0.862744978362,0.345097979377,0.490195988674,1],"ix":3},"o":{"a":0,"k":100,"ix":4},"w":{"a":0,"k":0,"ix":5},"lc":1,"lj":1,"ml":4,"bm":0,"nm":"Contour 1","mn":"ADBE Vector Graphic - Stroke","hd":false},{"ty":"fl","c":{"a":0,"k":[0.698039215686,0.01568627451,0.01568627451,1],"ix":4},"o":{"a":0,"k":100,"ix":5},"r":1,"bm":0,"nm":"Fond 1","mn":"ADBE Vector Graphic - Fill","hd":false},{"ty":"tr","p":{"a":1,"k":[{"i":{"x":0.667,"y":1},"o":{"x":0.333,"y":0},"t":17,"s":[99.848,116.452],"to":[-14.975,21.478],"ti":[14.975,-21.478]},{"t":23.0000009368092,"s":[9.998,245.318]}],"ix":2},"a":{"a":0,"k":[88.23,135.915],"ix":1},"s":{"a":0,"k":[100,100],"ix":3},"r":{"a":0,"k":0,"ix":6},"o":{"a":0,"k":100,"ix":7},"sk":{"a":0,"k":0,"ix":4},"sa":{"a":0,"k":0,"ix":5},"nm":"Transformer "}],"nm":"Forme 1","np":3,"cix":2,"bm":0,"ix":4,"mn":"ADBE Vector Group","hd":false},{"ty":"gr","it":[{"ind":0,"ty":"sh","ix":1,"ks":{"a":0,"k":{"i":[[2.739,2.298],[0,0],[-2.297,2.738],[0,0],[-2.738,-2.298],[0,0],[2.298,-2.739],[0,0]],"o":[[0,0],[-2.738,-2.298],[0,0],[2.298,-2.739],[0,0],[2.738,2.299],[0,0],[-2.299,2.738]],"v":[[-16.607,25.237],[-21.973,20.734],[-22.773,11.577],[7.449,-24.436],[16.605,-25.237],[21.971,-20.735],[22.773,-11.577],[-7.449,24.436]],"c":true},"ix":2},"nm":"Tracé 1","mn":"ADBE Vector Shape - Group","hd":false},{"ty":"fl","c":{"a":0,"k":[0.219999994016,0.195999998205,0.180000005984,1],"ix":4},"o":{"a":0,"k":100,"ix":5},"r":1,"bm":0,"nm":"Fond 1","mn":"ADBE Vector Graphic - Fill","hd":false},{"ty":"tr","p":{"a":0,"k":[27.18,27.785],"ix":2},"a":{"a":0,"k":[0,0],"ix":1},"s":{"a":0,"k":[100,100],"ix":3},"r":{"a":0,"k":0,"ix":6},"o":{"a":0,"k":100,"ix":7},"sk":{"a":0,"k":0,"ix":4},"sa":{"a":0,"k":0,"ix":5},"nm":"Transformer "}],"nm":"Groupe 1","np":2,"cix":2,"bm":0,"ix":5,"mn":"ADBE Vector Group","hd":false},{"ty":"gr","it":[{"ind":0,"ty":"sh","ix":1,"ks":{"a":0,"k":{"i":[[3.575,0],[0,0],[0,3.575],[0,0],[-3.575,0],[0,0],[0,-3.575],[0,0]],"o":[[0,0],[-3.575,0],[0,0],[0,-3.575],[0,0],[3.575,0],[0,0],[0,3.575]],"v":[[3.503,30.007],[-3.503,30.007],[-10.003,23.507],[-10.003,-23.507],[-3.503,-30.007],[3.503,-30.007],[10.003,-23.507],[10.003,23.507]],"c":true},"ix":2},"nm":"Tracé 1","mn":"ADBE Vector Shape - Group","hd":false},{"ty":"fl","c":{"a":0,"k":[0.219999994016,0.195999998205,0.180000005984,1],"ix":4},"o":{"a":0,"k":100,"ix":5},"r":1,"bm":0,"nm":"Fond 1","mn":"ADBE Vector Graphic - Fill","hd":false},{"ty":"tr","p":{"a":0,"k":[13.33,70.872],"ix":2},"a":{"a":0,"k":[0,0],"ix":1},"s":{"a":0,"k":[100,100],"ix":3},"r":{"a":0,"k":0,"ix":6},"o":{"a":0,"k":100,"ix":7},"sk":{"a":0,"k":0,"ix":4},"sa":{"a":0,"k":0,"ix":5},"nm":"Transformer "}],"nm":"Groupe 2","np":2,"cix":2,"bm":0,"ix":6,"mn":"ADBE Vector Group","hd":false},{"ty":"gr","it":[{"ind":0,"ty":"sh","ix":1,"ks":{"a":0,"k":{"i":[[0,-6.799],[6.799,0],[0,6.799],[-6.798,0]],"o":[[0,6.799],[-6.798,0],[0,-6.799],[6.799,0]],"v":[[12.311,0],[-0.001,12.311],[-12.311,0],[-0.001,-12.311]],"c":true},"ix":2},"nm":"Tracé 1","mn":"ADBE Vector Shape - Group","hd":false},{"ty":"fl","c":{"a":0,"k":[0.929000016755,0.702000038297,0.463000009574,1],"ix":4},"o":{"a":0,"k":100,"ix":5},"r":1,"bm":0,"nm":"Fond 1","mn":"ADBE Vector Graphic - Fill","hd":false},{"ty":"tr","p":{"a":0,"k":[12.561,105.495],"ix":2},"a":{"a":0,"k":[0,0],"ix":1},"s":{"a":0,"k":[100,100],"ix":3},"r":{"a":0,"k":0,"ix":6},"o":{"a":0,"k":100,"ix":7},"sk":{"a":0,"k":0,"ix":4},"sa":{"a":0,"k":0,"ix":5},"nm":"Transformer "}],"nm":"Groupe 3","np":2,"cix":2,"bm":0,"ix":7,"mn":"ADBE Vector Group","hd":false}],"ip":7.00000028511585,"op":156.850006388631,"st":7.00000028511585,"bm":0},{"ddd":0,"ind":2,"ty":4,"nm":"KNIFE/igor Silhouettes 2","parent":1,"sr":1,"ks":{"o":{"a":0,"k":100,"ix":11},"r":{"a":0,"k":33,"ix":10},"p":{"a":0,"k":[50.488,110.466,0],"ix":2},"a":{"a":0,"k":[47,30,0],"ix":1},"s":{"a":0,"k":[100,100,100],"ix":6}},"ao":0,"shapes":[{"ty":"gr","it":[{"ind":0,"ty":"sh","ix":1,"ks":{"a":0,"k":{"i":[[4,-2],[-2,-2],[0,0]],"o":[[0,0],[2,2],[0,0]],"v":[[-4,-6],[-2,-2],[3,-10]],"c":true},"ix":2},"nm":"Tracé 1","mn":"ADBE Vector Shape - Group","hd":false},{"ty":"fl","c":{"a":0,"k":[0.698000021542,0.016000001571,0.016000001571,1],"ix":4},"o":{"a":0,"k":100,"ix":5},"r":1,"bm":0,"nm":"Fond 1","mn":"ADBE Vector Graphic - Fill","hd":false},{"ty":"tr","p":{"a":0,"k":[89.175,10.25],"ix":2},"a":{"a":0,"k":[0,0],"ix":1},"s":{"a":0,"k":[100,100],"ix":3},"r":{"a":0,"k":0,"ix":6},"o":{"a":0,"k":100,"ix":7},"sk":{"a":0,"k":0,"ix":4},"sa":{"a":0,"k":0,"ix":5},"nm":"Transformer "}],"nm":"Groupe 1","np":2,"cix":2,"bm":0,"ix":1,"mn":"ADBE Vector Group","hd":false},{"ty":"gr","it":[{"ind":0,"ty":"sh","ix":1,"ks":{"a":0,"k":{"i":[[-0.263,-0.483],[0,0],[-0.483,0.263],[0,0],[0.263,0.483],[0,0],[0.483,-0.263],[0,0]],"o":[[0,0],[0.262,0.483],[0,0],[0.484,-0.263],[0,0],[-0.263,-0.483],[0,0],[-0.483,0.262]],"v":[[-1.43,0.314],[-1.042,1.029],[0.314,1.43],[1.028,1.042],[1.43,-0.314],[1.042,-1.029],[-0.314,-1.43],[-1.029,-1.041]],"c":true},"ix":2},"nm":"Tracé 1","mn":"ADBE Vector Shape - Group","hd":false},{"ty":"fl","c":{"a":0,"k":[1,1,1,1],"ix":4},"o":{"a":0,"k":100,"ix":5},"r":1,"bm":0,"nm":"Fond 1","mn":"ADBE Vector Graphic - Fill","hd":false},{"ty":"tr","p":{"a":0,"k":[39.516,32.462],"ix":2},"a":{"a":0,"k":[0,0],"ix":1},"s":{"a":0,"k":[100,100],"ix":3},"r":{"a":0,"k":0,"ix":6},"o":{"a":0,"k":100,"ix":7},"sk":{"a":0,"k":0,"ix":4},"sa":{"a":0,"k":0,"ix":5},"nm":"Transformer "}],"nm":"Groupe 2","np":2,"cix":2,"bm":0,"ix":2,"mn":"ADBE Vector Group","hd":false},{"ty":"gr","it":[{"ind":0,"ty":"sh","ix":1,"ks":{"a":0,"k":{"i":[[-0.476,-0.877],[0,0],[-0.876,0.476],[0,0],[0.476,0.876],[0,0],[0.877,-0.476],[0,0]],"o":[[0,0],[0.476,0.876],[0,0],[0.876,-0.476],[0,0],[-0.476,-0.877],[0,0],[-0.877,0.476]],"v":[[-21.876,8.347],[-18.908,13.812],[-16.449,14.539],[21.15,-5.889],[21.876,-8.347],[18.908,-13.812],[16.449,-14.54],[-21.148,5.888]],"c":true},"ix":2},"nm":"Tracé 1","mn":"ADBE Vector Shape - Group","hd":false},{"ty":"fl","c":{"a":0,"k":[0.277999997606,0.152999997606,0.043000000598,1],"ix":4},"o":{"a":0,"k":100,"ix":5},"r":1,"bm":0,"nm":"Fond 1","mn":"ADBE Vector Graphic - Fill","hd":false},{"ty":"tr","p":{"a":0,"k":[22.603,44.053],"ix":2},"a":{"a":0,"k":[0,0],"ix":1},"s":{"a":0,"k":[100,100],"ix":3},"r":{"a":0,"k":0,"ix":6},"o":{"a":0,"k":100,"ix":7},"sk":{"a":0,"k":0,"ix":4},"sa":{"a":0,"k":0,"ix":5},"nm":"Transformer "}],"nm":"Groupe 3","np":2,"cix":2,"bm":0,"ix":3,"mn":"ADBE Vector Group","hd":false},{"ty":"gr","it":[{"ind":0,"ty":"sh","ix":1,"ks":{"a":0,"k":{"i":[[38.77,-25.866],[0,0],[0,0]],"o":[[0,0],[0,0],[0,0]],"v":[[-15.827,24.324],[-26.572,4.55],[26.572,-24.324]],"c":true},"ix":2},"nm":"Tracé 1","mn":"ADBE Vector Shape - Group","hd":false},{"ty":"fl","c":{"a":0,"k":[0.698000021542,0.698000021542,0.698000021542,1],"ix":4},"o":{"a":0,"k":100,"ix":5},"r":1,"bm":0,"nm":"Fond 1","mn":"ADBE Vector Graphic - Fill","hd":false},{"ty":"tr","p":{"a":0,"k":[64.744,25.441],"ix":2},"a":{"a":0,"k":[0,0],"ix":1},"s":{"a":0,"k":[100,100],"ix":3},"r":{"a":0,"k":0,"ix":6},"o":{"a":0,"k":100,"ix":7},"sk":{"a":0,"k":0,"ix":4},"sa":{"a":0,"k":0,"ix":5},"nm":"Transformer "}],"nm":"Groupe 4","np":2,"cix":2,"bm":0,"ix":4,"mn":"ADBE Vector Group","hd":false},{"ty":"gr","it":[{"ind":0,"ty":"sh","ix":1,"ks":{"a":0,"k":{"i":[[38.392,-26.562],[0,0],[0,0]],"o":[[0,0],[0,0],[0,0]],"v":[[-13.814,26.178],[-26.572,2.696],[26.572,-26.178]],"c":true},"ix":2},"nm":"Tracé 1","mn":"ADBE Vector Shape - Group","hd":false},{"ty":"fl","c":{"a":0,"k":[0.819999964097,0.819999964097,0.819999964097,1],"ix":4},"o":{"a":0,"k":100,"ix":5},"r":1,"bm":0,"nm":"Fond 1","mn":"ADBE Vector Graphic - Fill","hd":false},{"ty":"tr","p":{"a":0,"k":[64.745,27.295],"ix":2},"a":{"a":0,"k":[0,0],"ix":1},"s":{"a":0,"k":[100,100],"ix":3},"r":{"a":0,"k":0,"ix":6},"o":{"a":0,"k":100,"ix":7},"sk":{"a":0,"k":0,"ix":4},"sa":{"a":0,"k":0,"ix":5},"nm":"Transformer "}],"nm":"Groupe 5","np":2,"cix":2,"bm":0,"ix":5,"mn":"ADBE Vector Group","hd":false}],"ip":7.00000028511585,"op":156.850006388631,"st":7.00000028511585,"bm":0},{"ddd":0,"ind":3,"ty":4,"nm":"face/igor Silhouettes","sr":1,"ks":{"o":{"a":0,"k":100,"ix":11},"r":{"a":0,"k":0,"ix":10},"p":{"a":0,"k":[185,169,0],"ix":2},"a":{"a":0,"k":[67,61.5,0],"ix":1},"s":{"a":0,"k":[100,100,100],"ix":6}},"ao":0,"shapes":[{"ty":"gr","it":[{"ind":0,"ty":"sh","ix":1,"ks":{"a":0,"k":{"i":[[-0.094,-2.717],[2.717,-0.094],[0.094,2.717],[-2.717,0.094]],"o":[[0.094,2.717],[-2.717,0.094],[-0.094,-2.717],[2.717,-0.094]],"v":[[4.92,-0.17],[0.17,4.92],[-4.92,0.17],[-0.17,-4.92]],"c":true},"ix":2},"nm":"Tracé 1","mn":"ADBE Vector Shape - Group","hd":false},{"ty":"fl","c":{"a":0,"k":[0,0,0,1],"ix":4},"o":{"a":0,"k":100,"ix":5},"r":1,"bm":0,"nm":"Fond 1","mn":"ADBE Vector Graphic - Fill","hd":false},{"ty":"tr","p":{"a":1,"k":[{"i":{"x":0.667,"y":1},"o":{"x":0.333,"y":0},"t":0,"s":[116.721,45.997],"to":[-1.375,0],"ti":[1.375,0]},{"i":{"x":0.667,"y":0.667},"o":{"x":0.333,"y":0.333},"t":10,"s":[108.471,45.997],"to":[0,0],"ti":[0,0]},{"i":{"x":0.667,"y":1},"o":{"x":0.167,"y":0},"t":30,"s":[108.471,45.997],"to":[1.375,0],"ti":[-1.375,0]},{"i":{"x":0.667,"y":0.667},"o":{"x":0.333,"y":0.333},"t":35,"s":[116.721,45.997],"to":[0,0],"ti":[0,0]},{"i":{"x":0.667,"y":1},"o":{"x":0.333,"y":0},"t":40,"s":[116.721,45.997],"to":[-1.375,0],"ti":[1.375,0]},{"i":{"x":0.667,"y":0.667},"o":{"x":0.167,"y":0.167},"t":45,"s":[108.471,45.997],"to":[0,0],"ti":[0,0]},{"i":{"x":0.667,"y":1},"o":{"x":0.167,"y":0},"t":115,"s":[108.471,45.997],"to":[0.625,0],"ti":[-0.625,0]},{"t":125.000005091354,"s":[112.221,45.997]}],"ix":2},"a":{"a":0,"k":[0,0],"ix":1},"s":{"a":0,"k":[100,100],"ix":3},"r":{"a":0,"k":0,"ix":6},"o":{"a":0,"k":100,"ix":7},"sk":{"a":0,"k":0,"ix":4},"sa":{"a":0,"k":0,"ix":5},"nm":"Transformer "}],"nm":"ojo","np":2,"cix":2,"bm":0,"ix":1,"mn":"ADBE Vector Group","hd":false},{"ty":"gr","it":[{"ind":0,"ty":"sh","ix":1,"ks":{"a":0,"k":{"i":[[-0.094,-2.717],[2.717,-0.093],[0.094,2.718],[-2.717,0.094]],"o":[[0.094,2.717],[-2.717,0.095],[-0.094,-2.716],[2.717,-0.094]],"v":[[4.92,-0.17],[0.17,4.919],[-4.92,0.169],[-0.17,-4.92]],"c":true},"ix":2},"nm":"Tracé 1","mn":"ADBE Vector Shape - Group","hd":false},{"ty":"fl","c":{"a":0,"k":[0,0,0,1],"ix":4},"o":{"a":0,"k":100,"ix":5},"r":1,"bm":0,"nm":"Fond 1","mn":"ADBE Vector Graphic - Fill","hd":false},{"ty":"tr","p":{"a":1,"k":[{"i":{"x":0.667,"y":1},"o":{"x":0.333,"y":0},"t":0,"s":[26.815,46.739],"to":[-2.292,0],"ti":[2.292,0]},{"i":{"x":0.667,"y":0.667},"o":{"x":0.333,"y":0.333},"t":10,"s":[13.065,46.739],"to":[0,0],"ti":[0,0]},{"i":{"x":0.667,"y":1},"o":{"x":0.167,"y":0},"t":30,"s":[13.065,46.739],"to":[2.292,0],"ti":[-2.292,0]},{"i":{"x":0.667,"y":0.667},"o":{"x":0.333,"y":0.333},"t":35,"s":[26.815,46.739],"to":[0,0],"ti":[0,0]},{"i":{"x":0.667,"y":1},"o":{"x":0.333,"y":0},"t":40,"s":[26.815,46.739],"to":[-2.292,0],"ti":[2.292,0]},{"i":{"x":0.667,"y":0.667},"o":{"x":0.167,"y":0.167},"t":45,"s":[13.065,46.739],"to":[0,0],"ti":[0,0]},{"i":{"x":0.667,"y":1},"o":{"x":0.167,"y":0},"t":115,"s":[13.065,46.739],"to":[1.083,0],"ti":[-1.083,0]},{"t":125.000005091354,"s":[19.565,46.739]}],"ix":2},"a":{"a":0,"k":[0,0],"ix":1},"s":{"a":0,"k":[100,100],"ix":3},"r":{"a":0,"k":0,"ix":6},"o":{"a":0,"k":100,"ix":7},"sk":{"a":0,"k":0,"ix":4},"sa":{"a":0,"k":0,"ix":5},"nm":"Transformer "}],"nm":"ojoo","np":2,"cix":2,"bm":0,"ix":2,"mn":"ADBE Vector Group","hd":false},{"ty":"gr","it":[{"ind":0,"ty":"sh","ix":1,"ks":{"a":0,"k":{"i":[[0,0],[0,0],[0,0]],"o":[[0,0],[0,0],[0,0]],"v":[[-3.376,-3.376],[-0.001,3.376],[3.376,-3.376]],"c":true},"ix":2},"nm":"Tracé 1","mn":"ADBE Vector Shape - Group","hd":false},{"ty":"fl","c":{"a":0,"k":[1,1,1,1],"ix":4},"o":{"a":0,"k":100,"ix":5},"r":1,"bm":0,"nm":"Fond 1","mn":"ADBE Vector Graphic - Fill","hd":false},{"ty":"tr","p":{"a":0,"k":[74.666,92.271],"ix":2},"a":{"a":0,"k":[0,0],"ix":1},"s":{"a":0,"k":[100,100],"ix":3},"r":{"a":0,"k":0,"ix":6},"o":{"a":0,"k":100,"ix":7},"sk":{"a":0,"k":0,"ix":4},"sa":{"a":0,"k":0,"ix":5},"nm":"Transformer "}],"nm":"Groupe 3","np":2,"cix":2,"bm":0,"ix":3,"mn":"ADBE Vector Group","hd":false},{"ty":"gr","it":[{"ind":0,"ty":"sh","ix":1,"ks":{"a":0,"k":{"i":[[0,0],[0,0],[0,0]],"o":[[0,0],[0,0],[0,0]],"v":[[-3.376,-3.376],[0,3.376],[3.376,-3.376]],"c":true},"ix":2},"nm":"Tracé 1","mn":"ADBE Vector Shape - Group","hd":false},{"ty":"fl","c":{"a":0,"k":[1,1,1,1],"ix":4},"o":{"a":0,"k":100,"ix":5},"r":1,"bm":0,"nm":"Fond 1","mn":"ADBE Vector Graphic - Fill","hd":false},{"ty":"tr","p":{"a":0,"k":[51.88,92.271],"ix":2},"a":{"a":0,"k":[0,0],"ix":1},"s":{"a":0,"k":[100,100],"ix":3},"r":{"a":0,"k":0,"ix":6},"o":{"a":0,"k":100,"ix":7},"sk":{"a":0,"k":0,"ix":4},"sa":{"a":0,"k":0,"ix":5},"nm":"Transformer "}],"nm":"Groupe 4","np":2,"cix":2,"bm":0,"ix":4,"mn":"ADBE Vector Group","hd":false},{"ty":"gr","it":[{"ind":0,"ty":"sh","ix":1,"ks":{"a":1,"k":[{"i":{"x":0.667,"y":1},"o":{"x":0.333,"y":0},"t":120,"s":[{"i":[[8.101,10.801],[0,0],[7.012,-4.402],[5.944,0.241]],"o":[[0,0],[0,0],[-4.383,2.751],[-7.271,-0.295]],"v":[[-25.318,-16.879],[25.318,-16.879],[13.872,-6.565],[-1.845,-1.894]],"c":true}]},{"t":145.000005905971,"s":[{"i":[[8.101,10.801],[0,0],[4.495,-1.209],[5.944,0.241]],"o":[[0,0],[0,0],[-4.997,1.344],[-7.271,-0.295]],"v":[[-25.318,-16.879],[25.318,-16.879],[14.497,-8.44],[-1.72,-6.894]],"c":true}]}],"ix":2},"nm":"Tracé 1","mn":"ADBE Vector Shape - Group","hd":false},{"ty":"fl","c":{"a":0,"k":[0.808000033509,0.216000007181,0.097999999102,1],"ix":4},"o":{"a":0,"k":100,"ix":5},"r":1,"bm":0,"nm":"Fond 1","mn":"ADBE Vector Graphic - Fill","hd":false},{"ty":"tr","p":{"a":0,"k":[64.651,95.438],"ix":2},"a":{"a":0,"k":[-0.731,-10.336],"ix":1},"s":{"a":0,"k":[100,100],"ix":3},"r":{"a":0,"k":0,"ix":6},"o":{"a":0,"k":100,"ix":7},"sk":{"a":0,"k":0,"ix":4},"sa":{"a":0,"k":0,"ix":5},"nm":"Transformer "}],"nm":"smile","np":2,"cix":2,"bm":0,"ix":5,"mn":"ADBE Vector Group","hd":false},{"ty":"gr","it":[{"ind":0,"ty":"sh","ix":1,"ks":{"a":0,"k":{"i":[[0,0],[0,0],[0,0],[0,0]],"o":[[0,0],[0,0],[0,0],[0,0]],"v":[[20.656,-1.279],[-19.035,8.122],[-20.656,1.278],[19.035,-8.122]],"c":true},"ix":2},"nm":"Tracé 1","mn":"ADBE Vector Shape - Group","hd":false},{"ty":"fl","c":{"a":0,"k":[0.277999997606,0.152999997606,0.043000000598,1],"ix":4},"o":{"a":0,"k":100,"ix":5},"r":1,"bm":0,"nm":"Fond 1","mn":"ADBE Vector Graphic - Fill","hd":false},{"ty":"tr","p":{"a":1,"k":[{"i":{"x":0.667,"y":1},"o":{"x":0.333,"y":0},"t":55,"s":[112.501,18.712],"to":[0,1.667],"ti":[0,-1.667]},{"t":70.0000028511585,"s":[112.501,28.712]}],"ix":2},"a":{"a":0,"k":[0,0],"ix":1},"s":{"a":0,"k":[100,100],"ix":3},"r":{"a":0,"k":0,"ix":6},"o":{"a":0,"k":100,"ix":7},"sk":{"a":0,"k":0,"ix":4},"sa":{"a":0,"k":0,"ix":5},"nm":"Transformer "}],"nm":"ceja","np":2,"cix":2,"bm":0,"ix":6,"mn":"ADBE Vector Group","hd":false},{"ty":"gr","it":[{"ind":0,"ty":"sh","ix":1,"ks":{"a":0,"k":{"i":[[0,0],[0,0],[0,0],[0,0]],"o":[[0,0],[0,0],[0,0],[0,0]],"v":[[15.905,13.242],[-19.421,-7.152],[-15.905,-13.242],[19.421,7.152]],"c":true},"ix":2},"nm":"Tracé 1","mn":"ADBE Vector Shape - Group","hd":false},{"ty":"fl","c":{"a":0,"k":[0.277999997606,0.152999997606,0.043000000598,1],"ix":4},"o":{"a":0,"k":100,"ix":5},"r":1,"bm":0,"nm":"Fond 1","mn":"ADBE Vector Graphic - Fill","hd":false},{"ty":"tr","p":{"a":1,"k":[{"i":{"x":0.667,"y":1},"o":{"x":0.333,"y":0},"t":55,"s":[19.671,13.493],"to":[0,-1.417],"ti":[0,1.417]},{"i":{"x":0.667,"y":0.667},"o":{"x":0.333,"y":0.333},"t":70,"s":[19.671,4.993],"to":[0,0],"ti":[0,0]},{"i":{"x":0.667,"y":1},"o":{"x":0.333,"y":0},"t":105,"s":[19.671,4.993],"to":[0,3.333],"ti":[0,-3.333]},{"t":115.000004684046,"s":[19.671,24.993]}],"ix":2},"a":{"a":0,"k":[0,0],"ix":1},"s":{"a":0,"k":[100,100],"ix":3},"r":{"a":0,"k":0,"ix":6},"o":{"a":0,"k":100,"ix":7},"sk":{"a":0,"k":0,"ix":4},"sa":{"a":0,"k":0,"ix":5},"nm":"Transformer "}],"nm":"cejaa","np":2,"cix":2,"bm":0,"ix":7,"mn":"ADBE Vector Group","hd":false},{"ty":"gr","it":[{"ind":0,"ty":"sh","ix":1,"ks":{"a":0,"k":{"i":[[0,-8.933],[5.05,0],[0,8.933],[-5.049,0]],"o":[[0,8.933],[-5.049,0],[0,-8.933],[5.05,0]],"v":[[9.143,0],[-0.001,16.175],[-9.143,0],[-0.001,-16.175]],"c":true},"ix":2},"nm":"Tracé 1","mn":"ADBE Vector Shape - Group","hd":false},{"ty":"fl","c":{"a":0,"k":[0.969000004787,0.889999988032,0.642999985639,1],"ix":4},"o":{"a":0,"k":100,"ix":5},"r":1,"bm":0,"nm":"Fond 1","mn":"ADBE Vector Graphic - Fill","hd":false},{"ty":"tr","p":{"a":0,"k":[112.501,43.184],"ix":2},"a":{"a":0,"k":[0,0],"ix":1},"s":{"a":0,"k":[100,100],"ix":3},"r":{"a":0,"k":0,"ix":6},"o":{"a":0,"k":100,"ix":7},"sk":{"a":0,"k":0,"ix":4},"sa":{"a":0,"k":0,"ix":5},"nm":"Transformer "}],"nm":"Groupe 8","np":2,"cix":2,"bm":0,"ix":8,"mn":"ADBE Vector Group","hd":false},{"ty":"gr","it":[{"ind":0,"ty":"sh","ix":1,"ks":{"a":0,"k":{"i":[[0,-11.264],[6.603,0],[0,11.264],[-6.603,0]],"o":[[0,11.264],[-6.603,0],[0,-11.264],[6.603,0]],"v":[[11.956,0],[-0.001,20.395],[-11.956,0],[-0.001,-20.395]],"c":true},"ix":2},"nm":"Tracé 1","mn":"ADBE Vector Shape - Group","hd":false},{"ty":"fl","c":{"a":0,"k":[0.969000004787,0.889999988032,0.642999985639,1],"ix":4},"o":{"a":0,"k":100,"ix":5},"r":1,"bm":0,"nm":"Fond 1","mn":"ADBE Vector Graphic - Fill","hd":false},{"ty":"tr","p":{"a":0,"k":[19.671,43.184],"ix":2},"a":{"a":0,"k":[0,0],"ix":1},"s":{"a":0,"k":[100,100],"ix":3},"r":{"a":0,"k":0,"ix":6},"o":{"a":0,"k":100,"ix":7},"sk":{"a":0,"k":0,"ix":4},"sa":{"a":0,"k":0,"ix":5},"nm":"Transformer "}],"nm":"Groupe 9","np":2,"cix":2,"bm":0,"ix":9,"mn":"ADBE Vector Group","hd":false}],"ip":0,"op":149.850006103516,"st":0,"bm":0},{"ddd":0,"ind":4,"ty":4,"nm":"BODY/igor Silhouettes","sr":1,"ks":{"o":{"a":0,"k":100,"ix":11},"r":{"a":0,"k":0,"ix":10},"p":{"a":0,"k":[185,253,0],"ix":2},"a":{"a":0,"k":[141,170.5,0],"ix":1},"s":{"a":0,"k":[100,100,100],"ix":6}},"ao":0,"shapes":[{"ty":"gr","it":[{"ind":0,"ty":"sh","ix":1,"ks":{"a":0,"k":{"i":[[-3.575,0],[0,0],[0,3.574],[0,0],[3.575,0],[0,0],[0,-3.575],[0,0]],"o":[[0,0],[3.575,0],[0,0],[0,-3.575],[0,0],[-3.575,0],[0,0],[0,3.574]],"v":[[-3.503,30.007],[3.502,30.007],[10.002,23.507],[10.002,-23.507],[3.502,-30.007],[-3.503,-30.007],[-10.003,-23.507],[-10.003,23.507]],"c":true},"ix":2},"nm":"Tracé 1","mn":"ADBE Vector Shape - Group","hd":false},{"ty":"fl","c":{"a":0,"k":[0.219999994016,0.195999998205,0.180000005984,1],"ix":4},"o":{"a":0,"k":100,"ix":5},"r":1,"bm":0,"nm":"Fond 1","mn":"ADBE Vector Graphic - Fill","hd":false},{"ty":"tr","p":{"a":0,"k":[177.999,293.153],"ix":2},"a":{"a":0,"k":[0,0],"ix":1},"s":{"a":0,"k":[100,100],"ix":3},"r":{"a":0,"k":0,"ix":6},"o":{"a":0,"k":100,"ix":7},"sk":{"a":0,"k":0,"ix":4},"sa":{"a":0,"k":0,"ix":5},"nm":"Transformer "}],"nm":"Groupe 1","np":2,"cix":2,"bm":0,"ix":1,"mn":"ADBE Vector Group","hd":false},{"ty":"gr","it":[{"ind":0,"ty":"sh","ix":1,"ks":{"a":0,"k":{"i":[[-3.575,0],[0,0],[0,3.574],[0,0],[3.575,0],[0,0],[0,-3.575],[0,0]],"o":[[0,0],[3.575,0],[0,0],[0,-3.575],[0,0],[-3.575,0],[0,0],[0,3.574]],"v":[[-3.503,30.007],[3.503,30.007],[10.003,23.507],[10.003,-23.507],[3.503,-30.007],[-3.503,-30.007],[-10.003,-23.507],[-10.003,23.507]],"c":true},"ix":2},"nm":"Tracé 1","mn":"ADBE Vector Shape - Group","hd":false},{"ty":"fl","c":{"a":0,"k":[0.219999994016,0.195999998205,0.180000005984,1],"ix":4},"o":{"a":0,"k":100,"ix":5},"r":1,"bm":0,"nm":"Fond 1","mn":"ADBE Vector Graphic - Fill","hd":false},{"ty":"tr","p":{"a":0,"k":[95.014,293.153],"ix":2},"a":{"a":0,"k":[0,0],"ix":1},"s":{"a":0,"k":[100,100],"ix":3},"r":{"a":0,"k":0,"ix":6},"o":{"a":0,"k":100,"ix":7},"sk":{"a":0,"k":0,"ix":4},"sa":{"a":0,"k":0,"ix":5},"nm":"Transformer "}],"nm":"Groupe 2","np":2,"cix":2,"bm":0,"ix":2,"mn":"ADBE Vector Group","hd":false},{"ty":"gr","it":[{"ind":0,"ty":"sh","ix":1,"ks":{"a":0,"k":{"i":[[0,-6.799],[-6.799,0],[0,6.799],[6.799,0]],"o":[[0,6.799],[6.799,0],[0,-6.799],[-6.799,0]],"v":[[-12.311,0],[-0.001,12.311],[12.31,0],[-0.001,-12.311]],"c":true},"ix":2},"nm":"Tracé 1","mn":"ADBE Vector Shape - Group","hd":false},{"ty":"fl","c":{"a":0,"k":[0.067000003889,0.030999998953,0.004000000393,1],"ix":4},"o":{"a":0,"k":100,"ix":5},"r":1,"bm":0,"nm":"Fond 1","mn":"ADBE Vector Graphic - Fill","hd":false},{"ty":"tr","p":{"a":0,"k":[177.648,327.94],"ix":2},"a":{"a":0,"k":[0,0],"ix":1},"s":{"a":0,"k":[100,100],"ix":3},"r":{"a":0,"k":0,"ix":6},"o":{"a":0,"k":100,"ix":7},"sk":{"a":0,"k":0,"ix":4},"sa":{"a":0,"k":0,"ix":5},"nm":"Transformer "}],"nm":"Groupe 3","np":2,"cix":2,"bm":0,"ix":3,"mn":"ADBE Vector Group","hd":false},{"ty":"gr","it":[{"ind":0,"ty":"sh","ix":1,"ks":{"a":0,"k":{"i":[[0,-6.799],[-6.799,0],[0,6.799],[6.798,0]],"o":[[0,6.799],[6.798,0],[0,-6.799],[-6.799,0]],"v":[[-12.311,0],[0.001,12.311],[12.311,0],[0.001,-12.311]],"c":true},"ix":2},"nm":"Tracé 1","mn":"ADBE Vector Shape - Group","hd":false},{"ty":"fl","c":{"a":0,"k":[0.067000003889,0.030999998953,0.004000000393,1],"ix":4},"o":{"a":0,"k":100,"ix":5},"r":1,"bm":0,"nm":"Fond 1","mn":"ADBE Vector Graphic - Fill","hd":false},{"ty":"tr","p":{"a":0,"k":[94.662,327.94],"ix":2},"a":{"a":0,"k":[0,0],"ix":1},"s":{"a":0,"k":[100,100],"ix":3},"r":{"a":0,"k":0,"ix":6},"o":{"a":0,"k":100,"ix":7},"sk":{"a":0,"k":0,"ix":4},"sa":{"a":0,"k":0,"ix":5},"nm":"Transformer "}],"nm":"Groupe 4","np":2,"cix":2,"bm":0,"ix":4,"mn":"ADBE Vector Group","hd":false},{"ty":"gr","it":[{"ind":0,"ty":"sh","ix":1,"ks":{"a":0,"k":{"i":[[0,-1.166],[1.165,0],[0,1.165],[-1.165,0]],"o":[[0,1.165],[-1.165,0],[0,-1.166],[1.165,0]],"v":[[2.11,0],[0,2.109],[-2.11,0],[0,-2.109]],"c":true},"ix":2},"nm":"Tracé 1","mn":"ADBE Vector Shape - Group","hd":false},{"ty":"fl","c":{"a":0,"k":[0.808000033509,0.545000023935,0.305999995213,1],"ix":4},"o":{"a":0,"k":100,"ix":5},"r":1,"bm":0,"nm":"Fond 1","mn":"ADBE Vector Graphic - Fill","hd":false},{"ty":"tr","p":{"a":0,"k":[225.997,64.247],"ix":2},"a":{"a":0,"k":[0,0],"ix":1},"s":{"a":0,"k":[100,100],"ix":3},"r":{"a":0,"k":0,"ix":6},"o":{"a":0,"k":100,"ix":7},"sk":{"a":0,"k":0,"ix":4},"sa":{"a":0,"k":0,"ix":5},"nm":"Transformer "}],"nm":"Groupe 5","np":2,"cix":2,"bm":0,"ix":5,"mn":"ADBE Vector Group","hd":false},{"ty":"gr","it":[{"ind":0,"ty":"sh","ix":1,"ks":{"a":0,"k":{"i":[[0,-1.554],[2.33,0],[0,1.554],[-2.331,0]],"o":[[0,1.554],[-2.331,0],[0,-1.554],[2.33,0]],"v":[[4.219,0],[0,2.813],[-4.22,0],[0,-2.813]],"c":true},"ix":2},"nm":"Tracé 1","mn":"ADBE Vector Shape - Group","hd":false},{"ty":"fl","c":{"a":0,"k":[0.808000033509,0.545000023935,0.305999995213,1],"ix":4},"o":{"a":0,"k":100,"ix":5},"r":1,"bm":0,"nm":"Fond 1","mn":"ADBE Vector Graphic - Fill","hd":false},{"ty":"tr","p":{"a":0,"k":[236.546,57.918],"ix":2},"a":{"a":0,"k":[0,0],"ix":1},"s":{"a":0,"k":[100,100],"ix":3},"r":{"a":0,"k":0,"ix":6},"o":{"a":0,"k":100,"ix":7},"sk":{"a":0,"k":0,"ix":4},"sa":{"a":0,"k":0,"ix":5},"nm":"Transformer "}],"nm":"Groupe 6","np":2,"cix":2,"bm":0,"ix":6,"mn":"ADBE Vector Group","hd":false},{"ty":"gr","it":[{"ind":0,"ty":"sh","ix":1,"ks":{"a":0,"k":{"i":[[0,-1.942],[1.943,0],[0,1.942],[-1.941,0]],"o":[[0,1.942],[-1.941,0],[0,-1.942],[1.943,0]],"v":[[3.516,0],[-0.001,3.517],[-3.517,0],[-0.001,-3.517]],"c":true},"ix":2},"nm":"Tracé 1","mn":"ADBE Vector Shape - Group","hd":false},{"ty":"fl","c":{"a":0,"k":[0.808000033509,0.545000023935,0.305999995213,1],"ix":4},"o":{"a":0,"k":100,"ix":5},"r":1,"bm":0,"nm":"Fond 1","mn":"ADBE Vector Graphic - Fill","hd":false},{"ty":"tr","p":{"a":0,"k":[224.59,54.401],"ix":2},"a":{"a":0,"k":[0,0],"ix":1},"s":{"a":0,"k":[100,100],"ix":3},"r":{"a":0,"k":0,"ix":6},"o":{"a":0,"k":100,"ix":7},"sk":{"a":0,"k":0,"ix":4},"sa":{"a":0,"k":0,"ix":5},"nm":"Transformer "}],"nm":"Groupe 7","np":2,"cix":2,"bm":0,"ix":7,"mn":"ADBE Vector Group","hd":false},{"ty":"gr","it":[{"ind":0,"ty":"sh","ix":1,"ks":{"a":0,"k":{"i":[[0,0],[0,0],[12.658,-19.692]],"o":[[0,0],[0,0],[-12.659,19.691]],"v":[[-17.581,3.516],[4.923,-33.053],[4.923,13.362]],"c":true},"ix":2},"nm":"Tracé 1","mn":"ADBE Vector Shape - Group","hd":false},{"ty":"fl","c":{"a":0,"k":[0.929000016755,0.702000038297,0.463000009574,1],"ix":4},"o":{"a":0,"k":100,"ix":5},"r":1,"bm":0,"nm":"Fond 1","mn":"ADBE Vector Graphic - Fill","hd":false},{"ty":"tr","p":{"a":0,"k":[263.822,71.436],"ix":2},"a":{"a":0,"k":[0,0],"ix":1},"s":{"a":0,"k":[100,100],"ix":3},"r":{"a":0,"k":0,"ix":6},"o":{"a":0,"k":100,"ix":7},"sk":{"a":0,"k":0,"ix":4},"sa":{"a":0,"k":0,"ix":5},"nm":"Transformer "}],"nm":"Groupe 8","np":2,"cix":2,"bm":0,"ix":8,"mn":"ADBE Vector Group","hd":false},{"ty":"gr","it":[{"ind":0,"ty":"sh","ix":1,"ks":{"a":0,"k":{"i":[[0,0],[0,0],[-12.659,-19.692]],"o":[[0,0],[0,0],[12.658,19.691]],"v":[[17.581,3.516],[-4.923,-33.053],[-4.923,13.362]],"c":true},"ix":2},"nm":"Tracé 1","mn":"ADBE Vector Shape - Group","hd":false},{"ty":"fl","c":{"a":0,"k":[0.929000016755,0.702000038297,0.463000009574,1],"ix":4},"o":{"a":0,"k":100,"ix":5},"r":1,"bm":0,"nm":"Fond 1","mn":"ADBE Vector Graphic - Fill","hd":false},{"ty":"tr","p":{"a":0,"k":[17.831,71.436],"ix":2},"a":{"a":0,"k":[0,0],"ix":1},"s":{"a":0,"k":[100,100],"ix":3},"r":{"a":0,"k":0,"ix":6},"o":{"a":0,"k":100,"ix":7},"sk":{"a":0,"k":0,"ix":4},"sa":{"a":0,"k":0,"ix":5},"nm":"Transformer "}],"nm":"Groupe 9","np":2,"cix":2,"bm":0,"ix":9,"mn":"ADBE Vector Group","hd":false},{"ty":"gr","it":[{"ind":0,"ty":"sh","ix":1,"ks":{"a":0,"k":{"i":[[0,-2.719],[8.545,0],[0,2.719],[-8.545,0]],"o":[[0,2.719],[-8.545,0],[0,-2.719],[8.545,0]],"v":[[15.471,0],[-0.001,4.923],[-15.472,0],[-0.001,-4.923]],"c":true},"ix":2},"nm":"Tracé 1","mn":"ADBE Vector Shape - Group","hd":false},{"ty":"fl","c":{"a":0,"k":[0.808000033509,0.545000023935,0.305999995213,1],"ix":4},"o":{"a":0,"k":100,"ix":5},"r":1,"bm":0,"nm":"Fond 1","mn":"ADBE Vector Graphic - Fill","hd":false},{"ty":"tr","p":{"a":0,"k":[140.902,82.532],"ix":2},"a":{"a":0,"k":[0,0],"ix":1},"s":{"a":0,"k":[100,100],"ix":3},"r":{"a":0,"k":0,"ix":6},"o":{"a":0,"k":100,"ix":7},"sk":{"a":0,"k":0,"ix":4},"sa":{"a":0,"k":0,"ix":5},"nm":"Transformer "}],"nm":"Groupe 10","np":2,"cix":2,"bm":0,"ix":10,"mn":"ADBE Vector Group","hd":false},{"ty":"gr","it":[{"ind":0,"ty":"sh","ix":1,"ks":{"a":0,"k":{"i":[[0,-43.89],[62.144,0],[0,43.889],[-62.144,0]],"o":[[0,43.889],[-62.144,0],[0,-43.89],[62.144,0]],"v":[[112.522,0],[0,79.469],[-112.522,0],[0,-79.469]],"c":true},"ix":2},"nm":"Tracé 1","mn":"ADBE Vector Shape - Group","hd":false},{"ty":"fl","c":{"a":0,"k":[0.929000016755,0.702000038297,0.463000009574,1],"ix":4},"o":{"a":0,"k":100,"ix":5},"r":1,"bm":0,"nm":"Fond 1","mn":"ADBE Vector Graphic - Fill","hd":false},{"ty":"tr","p":{"a":0,"k":[140.902,79.719],"ix":2},"a":{"a":0,"k":[0,0],"ix":1},"s":{"a":0,"k":[100,100],"ix":3},"r":{"a":0,"k":0,"ix":6},"o":{"a":0,"k":100,"ix":7},"sk":{"a":0,"k":0,"ix":4},"sa":{"a":0,"k":0,"ix":5},"nm":"Transformer "}],"nm":"Groupe 11","np":2,"cix":2,"bm":0,"ix":11,"mn":"ADBE Vector Group","hd":false},{"ty":"gr","it":[{"ind":0,"ty":"sh","ix":1,"ks":{"a":0,"k":{"i":[[0,0],[74.409,0],[18.24,-134.854]],"o":[[-4.132,-55.549],[0,0],[0,0]],"v":[[96.571,67.427],[-1.981,-57.754],[-96.571,67.427]],"c":true},"ix":2},"nm":"Tracé 1","mn":"ADBE Vector Shape - Group","hd":false},{"ty":"fl","c":{"a":0,"k":[0.219999994016,0.195999998205,0.180000005984,1],"ix":4},"o":{"a":0,"k":100,"ix":5},"r":1,"bm":0,"nm":"Fond 1","mn":"ADBE Vector Graphic - Fill","hd":false},{"ty":"tr","p":{"a":0,"k":[141.476,143.802],"ix":2},"a":{"a":0,"k":[0,0],"ix":1},"s":{"a":0,"k":[100,100],"ix":3},"r":{"a":0,"k":0,"ix":6},"o":{"a":0,"k":100,"ix":7},"sk":{"a":0,"k":0,"ix":4},"sa":{"a":0,"k":0,"ix":5},"nm":"Transformer "}],"nm":"Groupe 12","np":2,"cix":2,"bm":0,"ix":12,"mn":"ADBE Vector Group","hd":false},{"ty":"gr","it":[{"ind":0,"ty":"sh","ix":1,"ks":{"a":0,"k":{"i":[[0,0],[-0.104,-15.245],[0,0],[0.011,24.573]],"o":[[-0.929,12.937],[0,0],[0,0],[0,0]],"v":[[-97.63,-21.098],[-98.921,21.098],[96.588,21.098],[99.014,-21.098]],"c":true},"ix":2},"nm":"Tracé 1","mn":"ADBE Vector Shape - Group","hd":false},{"ty":"fl","c":{"a":0,"k":[0.219999994016,0.195999998205,0.180000005984,1],"ix":4},"o":{"a":0,"k":100,"ix":5},"r":1,"bm":0,"nm":"Fond 1","mn":"ADBE Vector Graphic - Fill","hd":false},{"ty":"tr","p":{"a":0,"k":[139.959,257.644],"ix":2},"a":{"a":0,"k":[0,0],"ix":1},"s":{"a":0,"k":[100,100],"ix":3},"r":{"a":0,"k":0,"ix":6},"o":{"a":0,"k":100,"ix":7},"sk":{"a":0,"k":0,"ix":4},"sa":{"a":0,"k":0,"ix":5},"nm":"Transformer "}],"nm":"Groupe 13","np":2,"cix":2,"bm":0,"ix":13,"mn":"ADBE Vector Group","hd":false},{"ty":"gr","it":[{"ind":0,"ty":"sh","ix":1,"ks":{"a":0,"k":{"i":[[-1.407,-205.353],[0,0],[123.774,0]],"o":[[0,0],[0,0],[0,0]],"v":[[-110.412,102.676],[85.094,102.676],[-11.955,-90.018]],"c":true},"ix":2},"nm":"Tracé 1","mn":"ADBE Vector Shape - Group","hd":false},{"ty":"fl","c":{"a":0,"k":[0.067000003889,0.030999998953,0.004000000393,1],"ix":4},"o":{"a":0,"k":100,"ix":5},"r":1,"bm":0,"nm":"Fond 1","mn":"ADBE Vector Graphic - Fill","hd":false},{"ty":"tr","p":{"a":0,"k":[151.895,176.066],"ix":2},"a":{"a":0,"k":[0,0],"ix":1},"s":{"a":0,"k":[100,100],"ix":3},"r":{"a":0,"k":0,"ix":6},"o":{"a":0,"k":100,"ix":7},"sk":{"a":0,"k":0,"ix":4},"sa":{"a":0,"k":0,"ix":5},"nm":"Transformer "}],"nm":"Groupe 14","np":2,"cix":2,"bm":0,"ix":14,"mn":"ADBE Vector Group","hd":false}],"ip":0,"op":149.850006103516,"st":0,"bm":0},{"ddd":0,"ind":5,"ty":4,"nm":"OTHER BRAS/igor Silhouettes","sr":1,"ks":{"o":{"a":0,"k":100,"ix":11},"r":{"a":1,"k":[{"i":{"x":[0.667],"y":[1]},"o":{"x":[0.333],"y":[0]},"t":0,"s":[-4.349]},{"t":7.00000028511585,"s":[33.651]}],"ix":10},"p":{"a":0,"k":[104,220,0],"ix":2},"a":{"a":0,"k":[40.5,6.5,0],"ix":1},"s":{"a":0,"k":[100,100,100],"ix":6}},"ao":0,"shapes":[{"ty":"gr","it":[{"ind":0,"ty":"sh","ix":1,"ks":{"a":0,"k":{"i":[[2.739,2.298],[0,0],[-2.297,2.738],[0,0],[-2.738,-2.298],[0,0],[2.298,-2.739],[0,0]],"o":[[0,0],[-2.738,-2.298],[0,0],[2.298,-2.739],[0,0],[2.738,2.299],[0,0],[-2.299,2.738]],"v":[[-16.607,25.237],[-21.973,20.734],[-22.773,11.577],[7.449,-24.436],[16.605,-25.237],[21.971,-20.735],[22.773,-11.577],[-7.449,24.436]],"c":true},"ix":2},"nm":"Tracé 1","mn":"ADBE Vector Shape - Group","hd":false},{"ty":"fl","c":{"a":0,"k":[0.219999994016,0.195999998205,0.180000005984,1],"ix":4},"o":{"a":0,"k":100,"ix":5},"r":1,"bm":0,"nm":"Fond 1","mn":"ADBE Vector Graphic - Fill","hd":false},{"ty":"tr","p":{"a":0,"k":[27.18,27.785],"ix":2},"a":{"a":0,"k":[0,0],"ix":1},"s":{"a":0,"k":[100,100],"ix":3},"r":{"a":0,"k":0,"ix":6},"o":{"a":0,"k":100,"ix":7},"sk":{"a":0,"k":0,"ix":4},"sa":{"a":0,"k":0,"ix":5},"nm":"Transformer "}],"nm":"Groupe 1","np":2,"cix":2,"bm":0,"ix":1,"mn":"ADBE Vector Group","hd":false},{"ty":"gr","it":[{"ind":0,"ty":"sh","ix":1,"ks":{"a":0,"k":{"i":[[3.575,0],[0,0],[0,3.575],[0,0],[-3.575,0],[0,0],[0,-3.575],[0,0]],"o":[[0,0],[-3.575,0],[0,0],[0,-3.575],[0,0],[3.575,0],[0,0],[0,3.575]],"v":[[3.503,30.007],[-3.503,30.007],[-10.003,23.507],[-10.003,-23.507],[-3.503,-30.007],[3.503,-30.007],[10.003,-23.507],[10.003,23.507]],"c":true},"ix":2},"nm":"Tracé 1","mn":"ADBE Vector Shape - Group","hd":false},{"ty":"fl","c":{"a":0,"k":[0.219999994016,0.195999998205,0.180000005984,1],"ix":4},"o":{"a":0,"k":100,"ix":5},"r":1,"bm":0,"nm":"Fond 1","mn":"ADBE Vector Graphic - Fill","hd":false},{"ty":"tr","p":{"a":0,"k":[13.33,70.872],"ix":2},"a":{"a":0,"k":[0,0],"ix":1},"s":{"a":0,"k":[100,100],"ix":3},"r":{"a":0,"k":0,"ix":6},"o":{"a":0,"k":100,"ix":7},"sk":{"a":0,"k":0,"ix":4},"sa":{"a":0,"k":0,"ix":5},"nm":"Transformer "}],"nm":"Groupe 2","np":2,"cix":2,"bm":0,"ix":2,"mn":"ADBE Vector Group","hd":false},{"ty":"gr","it":[{"ind":0,"ty":"sh","ix":1,"ks":{"a":0,"k":{"i":[[0,-6.799],[6.799,0],[0,6.799],[-6.798,0]],"o":[[0,6.799],[-6.798,0],[0,-6.799],[6.799,0]],"v":[[12.311,0],[-0.001,12.311],[-12.311,0],[-0.001,-12.311]],"c":true},"ix":2},"nm":"Tracé 1","mn":"ADBE Vector Shape - Group","hd":false},{"ty":"fl","c":{"a":0,"k":[0.929000016755,0.702000038297,0.463000009574,1],"ix":4},"o":{"a":0,"k":100,"ix":5},"r":1,"bm":0,"nm":"Fond 1","mn":"ADBE Vector Graphic - Fill","hd":false},{"ty":"tr","p":{"a":0,"k":[12.561,105.495],"ix":2},"a":{"a":0,"k":[0,0],"ix":1},"s":{"a":0,"k":[100,100],"ix":3},"r":{"a":0,"k":0,"ix":6},"o":{"a":0,"k":100,"ix":7},"sk":{"a":0,"k":0,"ix":4},"sa":{"a":0,"k":0,"ix":5},"nm":"Transformer "}],"nm":"Groupe 3","np":2,"cix":2,"bm":0,"ix":3,"mn":"ADBE Vector Group","hd":false}],"ip":0,"op":8.00000032584668,"st":0,"bm":0},{"ddd":0,"ind":6,"ty":4,"nm":"KNIFE/igor Silhouettes","parent":5,"sr":1,"ks":{"o":{"a":0,"k":100,"ix":11},"r":{"a":0,"k":33,"ix":10},"p":{"a":0,"k":[52.044,110.755,0],"ix":2},"a":{"a":0,"k":[47,30,0],"ix":1},"s":{"a":0,"k":[100,100,100],"ix":6}},"ao":0,"shapes":[{"ty":"gr","it":[{"ind":0,"ty":"sh","ix":1,"ks":{"a":0,"k":{"i":[[4,-2],[-2,-2],[0,-3],[-0.005,-0.499],[-0.828,0],[0,0],[-0.05,4.488],[0,0]],"o":[[0,0],[2,2],[0,0.515],[0.024,2.412],[1,0],[0,0],[0.05,-4.486],[0,0]],"v":[[-4,-6],[-2,-2],[2,4],[2.005,5.529],[3,10],[3,7],[1.95,-0.514],[3,-10]],"c":true},"ix":2},"nm":"Tracé 1","mn":"ADBE Vector Shape - Group","hd":false},{"ty":"fl","c":{"a":0,"k":[0.698000021542,0.016000001571,0.016000001571,1],"ix":4},"o":{"a":0,"k":100,"ix":5},"r":1,"bm":0,"nm":"Fond 1","mn":"ADBE Vector Graphic - Fill","hd":false},{"ty":"tr","p":{"a":0,"k":[89.175,10.25],"ix":2},"a":{"a":0,"k":[0,0],"ix":1},"s":{"a":0,"k":[100,100],"ix":3},"r":{"a":0,"k":0,"ix":6},"o":{"a":0,"k":100,"ix":7},"sk":{"a":0,"k":0,"ix":4},"sa":{"a":0,"k":0,"ix":5},"nm":"Transformer "}],"nm":"Groupe 1","np":2,"cix":2,"bm":0,"ix":1,"mn":"ADBE Vector Group","hd":false},{"ty":"gr","it":[{"ind":0,"ty":"sh","ix":1,"ks":{"a":0,"k":{"i":[[-0.263,-0.483],[0,0],[-0.483,0.263],[0,0],[0.263,0.483],[0,0],[0.483,-0.263],[0,0]],"o":[[0,0],[0.262,0.483],[0,0],[0.484,-0.263],[0,0],[-0.263,-0.483],[0,0],[-0.483,0.262]],"v":[[-1.43,0.314],[-1.042,1.029],[0.314,1.43],[1.028,1.042],[1.43,-0.314],[1.042,-1.029],[-0.314,-1.43],[-1.029,-1.041]],"c":true},"ix":2},"nm":"Tracé 1","mn":"ADBE Vector Shape - Group","hd":false},{"ty":"fl","c":{"a":0,"k":[1,1,1,1],"ix":4},"o":{"a":0,"k":100,"ix":5},"r":1,"bm":0,"nm":"Fond 1","mn":"ADBE Vector Graphic - Fill","hd":false},{"ty":"tr","p":{"a":0,"k":[39.516,32.462],"ix":2},"a":{"a":0,"k":[0,0],"ix":1},"s":{"a":0,"k":[100,100],"ix":3},"r":{"a":0,"k":0,"ix":6},"o":{"a":0,"k":100,"ix":7},"sk":{"a":0,"k":0,"ix":4},"sa":{"a":0,"k":0,"ix":5},"nm":"Transformer "}],"nm":"Groupe 2","np":2,"cix":2,"bm":0,"ix":2,"mn":"ADBE Vector Group","hd":false},{"ty":"gr","it":[{"ind":0,"ty":"sh","ix":1,"ks":{"a":0,"k":{"i":[[-0.476,-0.877],[0,0],[-0.876,0.476],[0,0],[0.476,0.876],[0,0],[0.877,-0.476],[0,0]],"o":[[0,0],[0.476,0.876],[0,0],[0.876,-0.476],[0,0],[-0.476,-0.877],[0,0],[-0.877,0.476]],"v":[[-21.876,8.347],[-18.908,13.812],[-16.449,14.539],[21.15,-5.889],[21.876,-8.347],[18.908,-13.812],[16.449,-14.54],[-21.148,5.888]],"c":true},"ix":2},"nm":"Tracé 1","mn":"ADBE Vector Shape - Group","hd":false},{"ty":"fl","c":{"a":0,"k":[0.277999997606,0.152999997606,0.043000000598,1],"ix":4},"o":{"a":0,"k":100,"ix":5},"r":1,"bm":0,"nm":"Fond 1","mn":"ADBE Vector Graphic - Fill","hd":false},{"ty":"tr","p":{"a":0,"k":[22.603,44.053],"ix":2},"a":{"a":0,"k":[0,0],"ix":1},"s":{"a":0,"k":[100,100],"ix":3},"r":{"a":0,"k":0,"ix":6},"o":{"a":0,"k":100,"ix":7},"sk":{"a":0,"k":0,"ix":4},"sa":{"a":0,"k":0,"ix":5},"nm":"Transformer "}],"nm":"Groupe 3","np":2,"cix":2,"bm":0,"ix":3,"mn":"ADBE Vector Group","hd":false},{"ty":"gr","it":[{"ind":0,"ty":"sh","ix":1,"ks":{"a":0,"k":{"i":[[38.77,-25.866],[0,0],[0,0]],"o":[[0,0],[0,0],[0,0]],"v":[[-15.827,24.324],[-26.572,4.55],[26.572,-24.324]],"c":true},"ix":2},"nm":"Tracé 1","mn":"ADBE Vector Shape - Group","hd":false},{"ty":"fl","c":{"a":0,"k":[0.698000021542,0.698000021542,0.698000021542,1],"ix":4},"o":{"a":0,"k":100,"ix":5},"r":1,"bm":0,"nm":"Fond 1","mn":"ADBE Vector Graphic - Fill","hd":false},{"ty":"tr","p":{"a":0,"k":[64.744,25.441],"ix":2},"a":{"a":0,"k":[0,0],"ix":1},"s":{"a":0,"k":[100,100],"ix":3},"r":{"a":0,"k":0,"ix":6},"o":{"a":0,"k":100,"ix":7},"sk":{"a":0,"k":0,"ix":4},"sa":{"a":0,"k":0,"ix":5},"nm":"Transformer "}],"nm":"Groupe 4","np":2,"cix":2,"bm":0,"ix":4,"mn":"ADBE Vector Group","hd":false},{"ty":"gr","it":[{"ind":0,"ty":"sh","ix":1,"ks":{"a":0,"k":{"i":[[38.392,-26.562],[0,0],[0,0]],"o":[[0,0],[0,0],[0,0]],"v":[[-13.814,26.178],[-26.572,2.696],[26.572,-26.178]],"c":true},"ix":2},"nm":"Tracé 1","mn":"ADBE Vector Shape - Group","hd":false},{"ty":"fl","c":{"a":0,"k":[0.819999964097,0.819999964097,0.819999964097,1],"ix":4},"o":{"a":0,"k":100,"ix":5},"r":1,"bm":0,"nm":"Fond 1","mn":"ADBE Vector Graphic - Fill","hd":false},{"ty":"tr","p":{"a":0,"k":[64.745,27.295],"ix":2},"a":{"a":0,"k":[0,0],"ix":1},"s":{"a":0,"k":[100,100],"ix":3},"r":{"a":0,"k":0,"ix":6},"o":{"a":0,"k":100,"ix":7},"sk":{"a":0,"k":0,"ix":4},"sa":{"a":0,"k":0,"ix":5},"nm":"Transformer "}],"nm":"Groupe 5","np":2,"cix":2,"bm":0,"ix":5,"mn":"ADBE Vector Group","hd":false}],"ip":0,"op":8.00000032584668,"st":0,"bm":0},{"ddd":0,"ind":7,"ty":4,"nm":"BRAS QUI TUE/igor Silhouettes","sr":1,"ks":{"o":{"a":0,"k":100,"ix":11},"r":{"a":1,"k":[{"i":{"x":[0.667],"y":[1]},"o":{"x":[0.333],"y":[0]},"t":65,"s":[12.095]},{"i":{"x":[0.667],"y":[1]},"o":{"x":[0.333],"y":[0]},"t":70,"s":[112.095]},{"t":80.0000032584668,"s":[-20.905]}],"ix":10},"p":{"a":0,"k":[259.429,225.016,0],"ix":2},"a":{"a":0,"k":[12.5,10.5,0],"ix":1},"s":{"a":0,"k":[100,100,100],"ix":6}},"ao":0,"shapes":[{"ty":"gr","it":[{"ind":0,"ty":"sh","ix":1,"ks":{"a":0,"k":{"i":[[-2.738,2.298],[0,0],[2.298,2.738],[0,0],[2.739,-2.298],[0,0],[-2.298,-2.739],[0,0]],"o":[[0,0],[2.738,-2.298],[0,0],[-2.299,-2.739],[0,0],[-2.739,2.298],[0,0],[2.298,2.738]],"v":[[16.606,25.238],[21.972,20.735],[22.773,11.578],[-7.449,-24.437],[-16.607,-25.238],[-21.972,-20.735],[-22.773,-11.577],[7.449,24.437]],"c":true},"ix":2},"nm":"Tracé 1","mn":"ADBE Vector Shape - Group","hd":false},{"ty":"fl","c":{"a":0,"k":[0.219999994016,0.195999998205,0.180000005984,1],"ix":4},"o":{"a":0,"k":100,"ix":5},"r":1,"bm":0,"nm":"Fond 1","mn":"ADBE Vector Graphic - Fill","hd":false},{"ty":"tr","p":{"a":0,"k":[25.321,27.785],"ix":2},"a":{"a":0,"k":[0,0],"ix":1},"s":{"a":0,"k":[100,100],"ix":3},"r":{"a":0,"k":0,"ix":6},"o":{"a":0,"k":100,"ix":7},"sk":{"a":0,"k":0,"ix":4},"sa":{"a":0,"k":0,"ix":5},"nm":"Transformer "}],"nm":"Groupe 1","np":2,"cix":2,"bm":0,"ix":1,"mn":"ADBE Vector Group","hd":false},{"ty":"gr","it":[{"ind":0,"ty":"sh","ix":1,"ks":{"a":0,"k":{"i":[[-1.939,3.004],[0,0],[3.004,1.939],[0,0],[1.939,-3.002],[0,0],[-3.004,-1.939],[0,0]],"o":[[0,0],[1.938,-3.004],[0,0],[-3.003,-1.94],[0,0],[-1.938,3.004],[0,0],[3.003,1.938]],"v":[[23.309,19.219],[27.109,13.335],[25.173,4.348],[-14.323,-21.153],[-23.309,-19.219],[-27.109,-13.334],[-25.173,-4.347],[14.323,21.155]],"c":true},"ix":2},"nm":"Tracé 1","mn":"ADBE Vector Shape - Group","hd":false},{"ty":"fl","c":{"a":0,"k":[0.219999994016,0.195999998205,0.180000005984,1],"ix":4},"o":{"a":0,"k":100,"ix":5},"r":1,"bm":0,"nm":"Fond 1","mn":"ADBE Vector Graphic - Fill","hd":false},{"ty":"tr","p":{"a":0,"k":[59.136,57.106],"ix":2},"a":{"a":0,"k":[0,0],"ix":1},"s":{"a":0,"k":[100,100],"ix":3},"r":{"a":0,"k":0,"ix":6},"o":{"a":0,"k":100,"ix":7},"sk":{"a":0,"k":0,"ix":4},"sa":{"a":0,"k":0,"ix":5},"nm":"Transformer "}],"nm":"Groupe 2","np":2,"cix":2,"bm":0,"ix":2,"mn":"ADBE Vector Group","hd":false},{"ty":"gr","it":[{"ind":0,"ty":"sh","ix":1,"ks":{"a":0,"k":{"i":[[-5.711,-3.688],[-3.688,5.712],[5.712,3.689],[3.687,-5.711]],"o":[[5.712,3.688],[3.688,-5.711],[-5.711,-3.687],[-3.689,5.712]],"v":[[-6.677,10.342],[10.343,6.677],[6.678,-10.343],[-10.341,-6.678]],"c":true},"ix":2},"nm":"Tracé 1","mn":"ADBE Vector Shape - Group","hd":false},{"ty":"fl","c":{"a":0,"k":[0.929000016755,0.702000038297,0.463000009574,1],"ix":4},"o":{"a":0,"k":100,"ix":5},"r":1,"bm":0,"nm":"Fond 1","mn":"ADBE Vector Graphic - Fill","hd":false},{"ty":"tr","p":{"a":0,"k":[88.64,75.241],"ix":2},"a":{"a":0,"k":[0,0],"ix":1},"s":{"a":0,"k":[100,100],"ix":3},"r":{"a":0,"k":0,"ix":6},"o":{"a":0,"k":100,"ix":7},"sk":{"a":0,"k":0,"ix":4},"sa":{"a":0,"k":0,"ix":5},"nm":"Transformer "}],"nm":"Groupe 3","np":2,"cix":2,"bm":0,"ix":3,"mn":"ADBE Vector Group","hd":false}],"ip":0,"op":149.850006103516,"st":0,"bm":0},{"ddd":0,"ind":8,"ty":4,"nm":"TETE MORTE/igor Silhouettes","sr":1,"ks":{"o":{"a":1,"k":[{"i":{"x":[0.667],"y":[1]},"o":{"x":[0.333],"y":[0]},"t":65,"s":[0]},{"t":70.0000028511585,"s":[100]}],"ix":11},"r":{"a":0,"k":12.095,"ix":10},"p":{"a":1,"k":[{"i":{"x":0.667,"y":0.597},"o":{"x":0.333,"y":0},"t":69,"s":[127,175,0],"to":[17.681,0.553,0],"ti":[-41.382,-1.293,0]},{"i":{"x":0.667,"y":1},"o":{"x":0.333,"y":0.325},"t":76,"s":[225.913,233.497,0],"to":[21.031,0.657,0],"ti":[-8.986,-0.281,0]},{"t":80.0000032584668,"s":[287,180,0]}],"ix":2},"a":{"a":0,"k":[-26.5,-52,0],"ix":1},"s":{"a":0,"k":[100,100,100],"ix":6}},"ao":0,"shapes":[{"ty":"gr","it":[{"ind":0,"ty":"sh","ix":1,"ks":{"a":0,"k":{"i":[[0,-0.553],[0.553,0],[0,0.553],[-0.553,0]],"o":[[0,0.553],[-0.553,0],[0,-0.553],[0.553,0]],"v":[[1,0],[0,1],[-1,0],[0,-1]],"c":true},"ix":2},"nm":"Tracé 1","mn":"ADBE Vector Shape - Group","hd":false},{"ty":"fl","c":{"a":0,"k":[0.847000002394,0.493999974868,0.20800000359,1],"ix":4},"o":{"a":0,"k":100,"ix":5},"r":1,"bm":0,"nm":"Fond 1","mn":"ADBE Vector Graphic - Fill","hd":false},{"ty":"tr","p":{"a":0,"k":[35.25,61.593],"ix":2},"a":{"a":0,"k":[0,0],"ix":1},"s":{"a":0,"k":[100,100],"ix":3},"r":{"a":0,"k":0,"ix":6},"o":{"a":0,"k":100,"ix":7},"sk":{"a":0,"k":0,"ix":4},"sa":{"a":0,"k":0,"ix":5},"nm":"Transformer "}],"nm":"Groupe 1","np":2,"cix":2,"bm":0,"ix":1,"mn":"ADBE Vector Group","hd":false},{"ty":"gr","it":[{"ind":0,"ty":"sh","ix":1,"ks":{"a":0,"k":{"i":[[0,-0.828],[0.553,0],[0,0.828],[-0.553,0]],"o":[[0,0.828],[-0.553,0],[0,-0.828],[0.553,0]],"v":[[1,0],[0,1.5],[-1,0],[0,-1.5]],"c":true},"ix":2},"nm":"Tracé 1","mn":"ADBE Vector Shape - Group","hd":false},{"ty":"fl","c":{"a":0,"k":[0.847000002394,0.493999974868,0.20800000359,1],"ix":4},"o":{"a":0,"k":100,"ix":5},"r":1,"bm":0,"nm":"Fond 1","mn":"ADBE Vector Graphic - Fill","hd":false},{"ty":"tr","p":{"a":0,"k":[31.25,63.093],"ix":2},"a":{"a":0,"k":[0,0],"ix":1},"s":{"a":0,"k":[100,100],"ix":3},"r":{"a":0,"k":0,"ix":6},"o":{"a":0,"k":100,"ix":7},"sk":{"a":0,"k":0,"ix":4},"sa":{"a":0,"k":0,"ix":5},"nm":"Transformer "}],"nm":"Groupe 2","np":2,"cix":2,"bm":0,"ix":2,"mn":"ADBE Vector Group","hd":false},{"ty":"gr","it":[{"ind":0,"ty":"sh","ix":1,"ks":{"a":0,"k":{"i":[[0,-0.553],[0.276,0],[0,0.553],[-0.276,0]],"o":[[0,0.553],[-0.276,0],[0,-0.553],[0.276,0]],"v":[[0.5,0],[0,1],[-0.5,0],[0,-1]],"c":true},"ix":2},"nm":"Tracé 1","mn":"ADBE Vector Shape - Group","hd":false},{"ty":"fl","c":{"a":0,"k":[0.847000002394,0.493999974868,0.20800000359,1],"ix":4},"o":{"a":0,"k":100,"ix":5},"r":1,"bm":0,"nm":"Fond 1","mn":"ADBE Vector Graphic - Fill","hd":false},{"ty":"tr","p":{"a":0,"k":[35.75,65.593],"ix":2},"a":{"a":0,"k":[0,0],"ix":1},"s":{"a":0,"k":[100,100],"ix":3},"r":{"a":0,"k":0,"ix":6},"o":{"a":0,"k":100,"ix":7},"sk":{"a":0,"k":0,"ix":4},"sa":{"a":0,"k":0,"ix":5},"nm":"Transformer "}],"nm":"Groupe 3","np":2,"cix":2,"bm":0,"ix":3,"mn":"ADBE Vector Group","hd":false},{"ty":"gr","it":[{"ind":0,"ty":"sh","ix":1,"ks":{"a":0,"k":{"i":[[0,-0.553],[0.553,0],[0,0.553],[-0.553,0]],"o":[[0,0.553],[-0.553,0],[0,-0.553],[0.553,0]],"v":[[1,0],[0,1],[-1,0],[0,-1]],"c":true},"ix":2},"nm":"Tracé 1","mn":"ADBE Vector Shape - Group","hd":false},{"ty":"fl","c":{"a":0,"k":[0.847000002394,0.493999974868,0.20800000359,1],"ix":4},"o":{"a":0,"k":100,"ix":5},"r":1,"bm":0,"nm":"Fond 1","mn":"ADBE Vector Graphic - Fill","hd":false},{"ty":"tr","p":{"a":0,"k":[115.25,52.593],"ix":2},"a":{"a":0,"k":[0,0],"ix":1},"s":{"a":0,"k":[100,100],"ix":3},"r":{"a":0,"k":0,"ix":6},"o":{"a":0,"k":100,"ix":7},"sk":{"a":0,"k":0,"ix":4},"sa":{"a":0,"k":0,"ix":5},"nm":"Transformer "}],"nm":"Groupe 4","np":2,"cix":2,"bm":0,"ix":4,"mn":"ADBE Vector Group","hd":false},{"ty":"gr","it":[{"ind":0,"ty":"sh","ix":1,"ks":{"a":0,"k":{"i":[[0,-0.828],[0.553,0],[0,0.828],[-0.553,0]],"o":[[0,0.828],[-0.553,0],[0,-0.828],[0.553,0]],"v":[[1,0],[0,1.5],[-1,0],[0,-1.5]],"c":true},"ix":2},"nm":"Tracé 1","mn":"ADBE Vector Shape - Group","hd":false},{"ty":"fl","c":{"a":0,"k":[0.847000002394,0.493999974868,0.20800000359,1],"ix":4},"o":{"a":0,"k":100,"ix":5},"r":1,"bm":0,"nm":"Fond 1","mn":"ADBE Vector Graphic - Fill","hd":false},{"ty":"tr","p":{"a":0,"k":[111.25,54.093],"ix":2},"a":{"a":0,"k":[0,0],"ix":1},"s":{"a":0,"k":[100,100],"ix":3},"r":{"a":0,"k":0,"ix":6},"o":{"a":0,"k":100,"ix":7},"sk":{"a":0,"k":0,"ix":4},"sa":{"a":0,"k":0,"ix":5},"nm":"Transformer "}],"nm":"Groupe 5","np":2,"cix":2,"bm":0,"ix":5,"mn":"ADBE Vector Group","hd":false},{"ty":"gr","it":[{"ind":0,"ty":"sh","ix":1,"ks":{"a":0,"k":{"i":[[0,-0.553],[0.276,0],[0,0.553],[-0.276,0]],"o":[[0,0.553],[-0.276,0],[0,-0.553],[0.276,0]],"v":[[0.5,0],[0,1],[-0.5,0],[0,-1]],"c":true},"ix":2},"nm":"Tracé 1","mn":"ADBE Vector Shape - Group","hd":false},{"ty":"fl","c":{"a":0,"k":[0.847000002394,0.493999974868,0.20800000359,1],"ix":4},"o":{"a":0,"k":100,"ix":5},"r":1,"bm":0,"nm":"Fond 1","mn":"ADBE Vector Graphic - Fill","hd":false},{"ty":"tr","p":{"a":0,"k":[115.75,56.593],"ix":2},"a":{"a":0,"k":[0,0],"ix":1},"s":{"a":0,"k":[100,100],"ix":3},"r":{"a":0,"k":0,"ix":6},"o":{"a":0,"k":100,"ix":7},"sk":{"a":0,"k":0,"ix":4},"sa":{"a":0,"k":0,"ix":5},"nm":"Transformer "}],"nm":"Groupe 6","np":2,"cix":2,"bm":0,"ix":6,"mn":"ADBE Vector Group","hd":false},{"ty":"gr","it":[{"ind":0,"ty":"sh","ix":1,"ks":{"a":0,"k":{"i":[[0,0],[0,0]],"o":[[0,0],[0,0]],"v":[[-40,2.5],[40,-2.5]],"c":false},"ix":2},"nm":"Tracé 1","mn":"ADBE Vector Shape - Group","hd":false},{"ty":"st","c":{"a":0,"k":[0,0,0,1],"ix":3},"o":{"a":0,"k":100,"ix":4},"w":{"a":0,"k":1,"ix":5},"lc":1,"lj":1,"ml":10,"bm":0,"nm":"Contour 1","mn":"ADBE Vector Graphic - Stroke","hd":false},{"ty":"tr","p":{"a":0,"k":[72.25,73.093],"ix":2},"a":{"a":0,"k":[0,0],"ix":1},"s":{"a":0,"k":[100,100],"ix":3},"r":{"a":0,"k":0,"ix":6},"o":{"a":0,"k":100,"ix":7},"sk":{"a":0,"k":0,"ix":4},"sa":{"a":0,"k":0,"ix":5},"nm":"Transformer "}],"nm":"Groupe 7","np":2,"cix":2,"bm":0,"ix":7,"mn":"ADBE Vector Group","hd":false},{"ty":"gr","it":[{"ind":0,"ty":"sh","ix":1,"ks":{"a":0,"k":{"i":[[4.933,-0.309],[0,0],[0.312,4.989],[0,0],[0,0],[0,0]],"o":[[0,0],[-4.988,0.312],[0,0],[0,0],[0,0],[0.308,4.932]],"v":[[0.581,6.611],[0.581,6.611],[-9.017,-1.859],[-9.263,-5.799],[8.702,-6.923],[8.955,-2.88]],"c":true},"ix":2},"nm":"Tracé 1","mn":"ADBE Vector Shape - Group","hd":false},{"ty":"fl","c":{"a":0,"k":[0.757000014361,0.152999997606,0.176000004189,1],"ix":4},"o":{"a":0,"k":100,"ix":5},"r":1,"bm":0,"nm":"Fond 1","mn":"ADBE Vector Graphic - Fill","hd":false},{"ty":"tr","p":{"a":0,"k":[73.125,78.967],"ix":2},"a":{"a":0,"k":[0,0],"ix":1},"s":{"a":0,"k":[100,100],"ix":3},"r":{"a":0,"k":0,"ix":6},"o":{"a":0,"k":100,"ix":7},"sk":{"a":0,"k":0,"ix":4},"sa":{"a":0,"k":0,"ix":5},"nm":"Transformer "}],"nm":"Groupe 8","np":2,"cix":2,"bm":0,"ix":8,"mn":"ADBE Vector Group","hd":false},{"ty":"gr","it":[{"ind":0,"ty":"sh","ix":1,"ks":{"a":0,"k":{"i":[[0,0],[0,0],[0,0],[0,0]],"o":[[0,0],[0,0],[0,0],[0,0]],"v":[[6.046,-8.276],[-4.143,9.374],[-6.046,8.277],[4.144,-9.374]],"c":true},"ix":2},"nm":"Tracé 1","mn":"ADBE Vector Shape - Group","hd":false},{"ty":"fl","c":{"a":0,"k":[0.149000010771,0.136999990426,0.125,1],"ix":4},"o":{"a":0,"k":100,"ix":5},"r":1,"bm":0,"nm":"Fond 1","mn":"ADBE Vector Graphic - Fill","hd":false},{"ty":"tr","p":{"a":0,"k":[92.718,34.22],"ix":2},"a":{"a":0,"k":[0,0],"ix":1},"s":{"a":0,"k":[100,100],"ix":3},"r":{"a":0,"k":0,"ix":6},"o":{"a":0,"k":100,"ix":7},"sk":{"a":0,"k":0,"ix":4},"sa":{"a":0,"k":0,"ix":5},"nm":"Transformer "}],"nm":"Groupe 9","np":2,"cix":2,"bm":0,"ix":9,"mn":"ADBE Vector Group","hd":false},{"ty":"gr","it":[{"ind":0,"ty":"sh","ix":1,"ks":{"a":0,"k":{"i":[[0,0],[0,0],[0,0],[0,0]],"o":[[0,0],[0,0],[0,0],[0,0]],"v":[[8.275,6.046],[-9.374,-4.144],[-8.277,-6.046],[9.374,4.144]],"c":true},"ix":2},"nm":"Tracé 1","mn":"ADBE Vector Shape - Group","hd":false},{"ty":"fl","c":{"a":0,"k":[0.149000010771,0.136999990426,0.125,1],"ix":4},"o":{"a":0,"k":100,"ix":5},"r":1,"bm":0,"nm":"Fond 1","mn":"ADBE Vector Graphic - Fill","hd":false},{"ty":"tr","p":{"a":0,"k":[92.798,34.449],"ix":2},"a":{"a":0,"k":[0,0],"ix":1},"s":{"a":0,"k":[100,100],"ix":3},"r":{"a":0,"k":0,"ix":6},"o":{"a":0,"k":100,"ix":7},"sk":{"a":0,"k":0,"ix":4},"sa":{"a":0,"k":0,"ix":5},"nm":"Transformer "}],"nm":"Groupe 10","np":2,"cix":2,"bm":0,"ix":10,"mn":"ADBE Vector Group","hd":false},{"ty":"gr","it":[{"ind":0,"ty":"sh","ix":1,"ks":{"a":0,"k":{"i":[[0,0],[0,0],[0,0],[0,0]],"o":[[0,0],[0,0],[0,0],[0,0]],"v":[[6.046,-8.276],[-4.143,9.374],[-6.046,8.277],[4.145,-9.374]],"c":true},"ix":2},"nm":"Tracé 1","mn":"ADBE Vector Shape - Group","hd":false},{"ty":"fl","c":{"a":0,"k":[0.149000010771,0.136999990426,0.125,1],"ix":4},"o":{"a":0,"k":100,"ix":5},"r":1,"bm":0,"nm":"Fond 1","mn":"ADBE Vector Graphic - Fill","hd":false},{"ty":"tr","p":{"a":0,"k":[40.797,39.22],"ix":2},"a":{"a":0,"k":[0,0],"ix":1},"s":{"a":0,"k":[100,100],"ix":3},"r":{"a":0,"k":0,"ix":6},"o":{"a":0,"k":100,"ix":7},"sk":{"a":0,"k":0,"ix":4},"sa":{"a":0,"k":0,"ix":5},"nm":"Transformer "}],"nm":"Groupe 11","np":2,"cix":2,"bm":0,"ix":11,"mn":"ADBE Vector Group","hd":false},{"ty":"gr","it":[{"ind":0,"ty":"sh","ix":1,"ks":{"a":0,"k":{"i":[[0,0],[0,0],[0,0],[0,0]],"o":[[0,0],[0,0],[0,0],[0,0]],"v":[[8.276,6.046],[-9.374,-4.144],[-8.276,-6.046],[9.374,4.144]],"c":true},"ix":2},"nm":"Tracé 1","mn":"ADBE Vector Shape - Group","hd":false},{"ty":"fl","c":{"a":0,"k":[0.149000010771,0.136999990426,0.125,1],"ix":4},"o":{"a":0,"k":100,"ix":5},"r":1,"bm":0,"nm":"Fond 1","mn":"ADBE Vector Graphic - Fill","hd":false},{"ty":"tr","p":{"a":0,"k":[40.877,39.449],"ix":2},"a":{"a":0,"k":[0,0],"ix":1},"s":{"a":0,"k":[100,100],"ix":3},"r":{"a":0,"k":0,"ix":6},"o":{"a":0,"k":100,"ix":7},"sk":{"a":0,"k":0,"ix":4},"sa":{"a":0,"k":0,"ix":5},"nm":"Transformer "}],"nm":"Groupe 12","np":2,"cix":2,"bm":0,"ix":12,"mn":"ADBE Vector Group","hd":false},{"ty":"gr","it":[{"ind":0,"ty":"sh","ix":1,"ks":{"a":0,"k":{"i":[[0,-2.808],[5.964,0],[0,2.808],[-5.964,0]],"o":[[0,2.808],[-5.964,0],[0,-2.808],[5.964,0]],"v":[[10.798,0],[0,5.084],[-10.798,0],[0,-5.084]],"c":true},"ix":2},"nm":"Tracé 1","mn":"ADBE Vector Shape - Group","hd":false},{"ty":"fl","c":{"a":0,"k":[0.808000033509,0.545000023935,0.305999995213,1],"ix":4},"o":{"a":0,"k":100,"ix":5},"r":1,"bm":0,"nm":"Fond 1","mn":"ADBE Vector Graphic - Fill","hd":false},{"ty":"tr","p":{"a":0,"k":[71.452,59.677],"ix":2},"a":{"a":0,"k":[0,0],"ix":1},"s":{"a":0,"k":[100,100],"ix":3},"r":{"a":0,"k":0,"ix":6},"o":{"a":0,"k":100,"ix":7},"sk":{"a":0,"k":0,"ix":4},"sa":{"a":0,"k":0,"ix":5},"nm":"Transformer "}],"nm":"Groupe 13","np":2,"cix":2,"bm":0,"ix":13,"mn":"ADBE Vector Group","hd":false},{"ty":"gr","it":[{"ind":0,"ty":"sh","ix":1,"ks":{"a":0,"k":{"i":[[0,0],[0,0],[0,0],[0,0]],"o":[[0,0],[0,0],[0,0],[0,0]],"v":[[-2.153,5.712],[0.796,-6.052],[2.153,-5.712],[-0.798,6.052]],"c":true},"ix":2},"nm":"Tracé 1","mn":"ADBE Vector Shape - Group","hd":false},{"ty":"fl","c":{"a":0,"k":[0.458999992819,0.301999978458,0.156999999402,1],"ix":4},"o":{"a":0,"k":100,"ix":5},"r":1,"bm":0,"nm":"Fond 1","mn":"ADBE Vector Graphic - Fill","hd":false},{"ty":"tr","p":{"a":0,"k":[95.703,8.362],"ix":2},"a":{"a":0,"k":[0,0],"ix":1},"s":{"a":0,"k":[100,100],"ix":3},"r":{"a":0,"k":0,"ix":6},"o":{"a":0,"k":100,"ix":7},"sk":{"a":0,"k":0,"ix":4},"sa":{"a":0,"k":0,"ix":5},"nm":"Transformer "}],"nm":"Groupe 14","np":2,"cix":2,"bm":0,"ix":14,"mn":"ADBE Vector Group","hd":false},{"ty":"gr","it":[{"ind":0,"ty":"sh","ix":1,"ks":{"a":0,"k":{"i":[[0,0],[0,0],[0,0],[0,0]],"o":[[0,0],[0,0],[0,0],[0,0]],"v":[[-0.699,-6.064],[0.699,-6.064],[0.699,6.064],[-0.699,6.064]],"c":true},"ix":2},"nm":"Tracé 1","mn":"ADBE Vector Shape - Group","hd":false},{"ty":"fl","c":{"a":0,"k":[0.458999992819,0.301999978458,0.156999999402,1],"ix":4},"o":{"a":0,"k":100,"ix":5},"r":1,"bm":0,"nm":"Fond 1","mn":"ADBE Vector Graphic - Fill","hd":false},{"ty":"tr","p":{"a":0,"k":[71.461,6.314],"ix":2},"a":{"a":0,"k":[0,0],"ix":1},"s":{"a":0,"k":[100,100],"ix":3},"r":{"a":0,"k":0,"ix":6},"o":{"a":0,"k":100,"ix":7},"sk":{"a":0,"k":0,"ix":4},"sa":{"a":0,"k":0,"ix":5},"nm":"Transformer "}],"nm":"Groupe 15","np":2,"cix":2,"bm":0,"ix":15,"mn":"ADBE Vector Group","hd":false},{"ty":"gr","it":[{"ind":0,"ty":"sh","ix":1,"ks":{"a":0,"k":{"i":[[0,0],[0,0],[0,0],[0,0]],"o":[[0,0],[0,0],[0,0],[0,0]],"v":[[0.894,6.038],[-2.245,-5.676],[-0.894,-6.038],[2.245,5.676]],"c":true},"ix":2},"nm":"Tracé 1","mn":"ADBE Vector Shape - Group","hd":false},{"ty":"fl","c":{"a":0,"k":[0.458999992819,0.301999978458,0.156999999402,1],"ix":4},"o":{"a":0,"k":100,"ix":5},"r":1,"bm":0,"nm":"Fond 1","mn":"ADBE Vector Graphic - Fill","hd":false},{"ty":"tr","p":{"a":0,"k":[46.144,8.632],"ix":2},"a":{"a":0,"k":[0,0],"ix":1},"s":{"a":0,"k":[100,100],"ix":3},"r":{"a":0,"k":0,"ix":6},"o":{"a":0,"k":100,"ix":7},"sk":{"a":0,"k":0,"ix":4},"sa":{"a":0,"k":0,"ix":5},"nm":"Transformer "}],"nm":"Groupe 16","np":2,"cix":2,"bm":0,"ix":16,"mn":"ADBE Vector Group","hd":false},{"ty":"gr","it":[{"ind":0,"ty":"sh","ix":1,"ks":{"a":0,"k":{"i":[[0,-3.313],[3.313,0],[0,3.313],[-3.313,0]],"o":[[0,3.313],[-3.313,0],[0,-3.313],[3.313,0]],"v":[[6,0],[0,6],[-6,0],[0,-6]],"c":true},"ix":2},"nm":"Tracé 1","mn":"ADBE Vector Shape - Group","hd":false},{"ty":"fl","c":{"a":0,"k":[0.957000014361,0.736999990426,0.536999990426,1],"ix":4},"o":{"a":0,"k":100,"ix":5},"r":1,"bm":0,"nm":"Fond 1","mn":"ADBE Vector Graphic - Fill","hd":false},{"ty":"tr","p":{"a":0,"k":[6.25,47.593],"ix":2},"a":{"a":0,"k":[0,0],"ix":1},"s":{"a":0,"k":[100,100],"ix":3},"r":{"a":0,"k":0,"ix":6},"o":{"a":0,"k":100,"ix":7},"sk":{"a":0,"k":0,"ix":4},"sa":{"a":0,"k":0,"ix":5},"nm":"Transformer "}],"nm":"Groupe 17","np":2,"cix":2,"bm":0,"ix":17,"mn":"ADBE Vector Group","hd":false},{"ty":"gr","it":[{"ind":0,"ty":"sh","ix":1,"ks":{"a":0,"k":{"i":[[0,-3.313],[3.313,0],[0,3.313],[-3.313,0]],"o":[[0,3.313],[-3.313,0],[0,-3.313],[3.313,0]],"v":[[6,0],[0,6],[-6,0],[0,-6]],"c":true},"ix":2},"nm":"Tracé 1","mn":"ADBE Vector Shape - Group","hd":false},{"ty":"fl","c":{"a":0,"k":[0.957000014361,0.736999990426,0.536999990426,1],"ix":4},"o":{"a":0,"k":100,"ix":5},"r":1,"bm":0,"nm":"Fond 1","mn":"ADBE Vector Graphic - Fill","hd":false},{"ty":"tr","p":{"a":0,"k":[136.25,45.593],"ix":2},"a":{"a":0,"k":[0,0],"ix":1},"s":{"a":0,"k":[100,100],"ix":3},"r":{"a":0,"k":0,"ix":6},"o":{"a":0,"k":100,"ix":7},"sk":{"a":0,"k":0,"ix":4},"sa":{"a":0,"k":0,"ix":5},"nm":"Transformer "}],"nm":"Groupe 18","np":2,"cix":2,"bm":0,"ix":18,"mn":"ADBE Vector Group","hd":false},{"ty":"gr","it":[{"ind":0,"ty":"sh","ix":1,"ks":{"a":0,"k":{"i":[[0,-24.504],[34.696,0],[0,24.505],[-34.697,0]],"o":[[0,24.505],[-34.697,0],[0,-24.504],[34.696,0]],"v":[[62.823,-0.001],[0,44.368],[-62.823,-0.001],[0,-44.368]],"c":true},"ix":2},"nm":"Tracé 1","mn":"ADBE Vector Shape - Group","hd":false},{"ty":"fl","c":{"a":0,"k":[0.957000014361,0.736999990426,0.536999990426,1],"ix":4},"o":{"a":0,"k":100,"ix":5},"r":1,"bm":0,"nm":"Fond 1","mn":"ADBE Vector Graphic - Fill","hd":false},{"ty":"tr","p":{"a":0,"k":[71.427,52.938],"ix":2},"a":{"a":0,"k":[0,0],"ix":1},"s":{"a":0,"k":[100,100],"ix":3},"r":{"a":0,"k":0,"ix":6},"o":{"a":0,"k":100,"ix":7},"sk":{"a":0,"k":0,"ix":4},"sa":{"a":0,"k":0,"ix":5},"nm":"Transformer "}],"nm":"Groupe 19","np":2,"cix":2,"bm":0,"ix":19,"mn":"ADBE Vector Group","hd":false}],"ip":65.0000026475043,"op":149.850006103516,"st":0,"bm":0}],"markers":[]}